starlette_resource/__init__.py
starlette_resource/resource.py
starlette_resource/websocket_resource.py
starlette_resource-0.1.1.dist-info/METADATA
starlette_resource-0.1.1.dist-info/WHEEL
starlette_resource-0.1.1.dist-info/RECORD
