Metadata-Version: 2.1
Name: starlette-resource
Version: 0.1.1
Summary: Starlette resource that helps you follow a layered architecture.
License: MIT
Author: Gabriel Couture
Requires-Python: >=3.8,<4.0
Classifier: License :: OSI Approved :: MIT License
Classifier: Programming Language :: Python :: 3
Classifier: Programming Language :: Python :: 3.8
Classifier: Programming Language :: Python :: 3.9
Classifier: Programming Language :: Python :: 3.10
Classifier: Programming Language :: Python :: 3.11
Requires-Dist: starlette (>=0.31.1,<0.32.0)
